mocores/__init__.py
mocores/client.py
mocores/worker.py
mocores/common/__init__.py
mocores/core/__init__.py
mocores/core/actor.py
mocores/core/membership_table.py
mocores/core/task.py
mocores/core/work_item.py
mocores/net/__init__.py
mocores/net/protocol.py
mocores/net/tcp_client.py
mocores/net/tcp_server.py
mocores-0.1.1.dist-info/DESCRIPTION.rst
mocores-0.1.1.dist-info/METADATA
mocores-0.1.1.dist-info/RECORD
mocores-0.1.1.dist-info/WHEEL
mocores-0.1.1.dist-info/metadata.json
mocores-0.1.1.dist-info/top_level.txt
