Metadata-Version: 2.0
Name: mocores
Version: 0.1.1
Summary: A distributed, high-scale computing system
Home-page: https://github.com/toyteam/Mocores
Author: JasonWang
Author-email: jstzwj@aliyun.com
License: MIT Licence
Keywords: pip,actor-model,cloud-computing,distributed-systems
Platform: any
